network_wrangler/__init__.py
network_wrangler/logger.py
network_wrangler/params.py
network_wrangler/scenario.py
network_wrangler/time.py
network_wrangler/viz.py
network_wrangler/models/__init__.py
network_wrangler/models/_base/__init__.py
network_wrangler/models/_base/db.py
network_wrangler/models/_base/geo.py
network_wrangler/models/_base/records.py
network_wrangler/models/_base/root.py
network_wrangler/models/_base/tables.py
network_wrangler/models/_base/types.py
network_wrangler/models/_base/validate.py
network_wrangler/models/gtfs/__init__.py
network_wrangler/models/gtfs/gtfs.py
network_wrangler/models/gtfs/records.py
network_wrangler/models/gtfs/table_types.py
network_wrangler/models/gtfs/tables.py
network_wrangler/models/gtfs/types.py
network_wrangler/models/projects/__init__.py
network_wrangler/models/projects/roadway_deletion.py
network_wrangler/models/projects/roadway_property_change.py
network_wrangler/models/projects/roadway_selection.py
network_wrangler/models/projects/transit_selection.py
network_wrangler/models/roadway/__init__.py
network_wrangler/models/roadway/tables.py
network_wrangler/models/roadway/types.py
network_wrangler/roadway/__init__.py
network_wrangler/roadway/clip.py
network_wrangler/roadway/graph.py
network_wrangler/roadway/io.py
network_wrangler/roadway/model_roadway.py
network_wrangler/roadway/network.py
network_wrangler/roadway/segment.py
network_wrangler/roadway/selection.py
network_wrangler/roadway/subnet.py
network_wrangler/roadway/utils.py
network_wrangler/roadway/viz.py
network_wrangler/roadway/__pycache__/df_acce
network_wrangler/roadway/links/__init__.py
network_wrangler/roadway/links/create.py
network_wrangler/roadway/links/delete.py
network_wrangler/roadway/links/df_accessors.py
network_wrangler/roadway/links/edit.py
network_wrangler/roadway/links/filters.py
network_wrangler/roadway/links/geo.py
network_wrangler/roadway/links/io.py
network_wrangler/roadway/links/links.py
network_wrangler/roadway/links/scopes.py
network_wrangler-0.3.0.dist-info/LICENSE
network_wrangler-0.3.0.dist-info/METADATA
network_wrangler-0.3.0.dist-info/WHEEL
network_wrangler-0.3.0.dist-info/top_level.txt
network_wrangler-0.3.0.dist-info/RECORD
