Metadata-Version: 2.1
Name: network-wrangler
Version: 0.3.0
Author-email: Elizabeth Sall <elizabeth@urbanlabs.io>, Sijia Wang <Sijia.Wang@wsp.com>, Lisa Zorn <lzorn@bayareametro.gov>, Ashish Kulshrestha <Ashish.Kulshrestha@wsp.com>
License: Apache License
Classifier: Development Status :: 1 - Planning
Classifier: License :: OSI Approved :: Apache Software License
Classifier: Natural Language :: English
Classifier: Operating System :: OS Independent
Classifier: Programming Language :: Python
Classifier: Programming Language :: Python :: 3
License-File: LICENSE
Requires-Dist: geographiclib
Requires-Dist: geojson
Requires-Dist: geopandas >=0.8.0
Requires-Dist: osmnx >=0.12
Requires-Dist: pandas >=1.6
Requires-Dist: pandera[geopandas]
Requires-Dist: projectcard
Requires-Dist: pyarrow
Requires-Dist: pydantic >=2
Requires-Dist: pyogrio
Requires-Dist: pyyaml
Provides-Extra: docs
Requires-Dist: fontawesome-markdown ; extra == 'docs'
Requires-Dist: jupyter ; extra == 'docs'
Requires-Dist: markdown ==3.3.1 ; extra == 'docs'
Requires-Dist: mike <2.0 ; extra == 'docs'
Requires-Dist: mkdocs ; extra == 'docs'
Requires-Dist: mkdocs-autorefs ; extra == 'docs'
Requires-Dist: mkdocs-awesome-pages-plugin ; extra == 'docs'
Requires-Dist: mkdocs-jupyter ; extra == 'docs'
Requires-Dist: mkdocs-macros-plugin ; extra == 'docs'
Requires-Dist: mkdocs-material ; extra == 'docs'
Requires-Dist: mkdocstrings ; extra == 'docs'
Requires-Dist: mkdocstrings-python ; extra == 'docs'
Provides-Extra: tests
Requires-Dist: coverage ; extra == 'tests'
Requires-Dist: mypy ; extra == 'tests'
Requires-Dist: pytest ; extra == 'tests'
Requires-Dist: pytest-benchmark ; extra == 'tests'
Requires-Dist: pytest-cov ; extra == 'tests'
Requires-Dist: ruff ; extra == 'tests'
Requires-Dist: vulture ; extra == 'tests'
Provides-Extra: viz
Requires-Dist: folium ; extra == 'viz'
Requires-Dist: jupyter ; extra == 'viz'
Requires-Dist: notebook ; extra == 'viz'
